microdegree_management/.gitignore
microdegree_management/__init__.py
microdegree_management/main.py
microdegree_management-1.3.0.dist-info/entry_points.txt
microdegree_management-1.3.0.dist-info/WHEEL
microdegree_management-1.3.0.dist-info/METADATA
microdegree_management-1.3.0.dist-info/RECORD
