Metadata-Version: 2.1
Name: microdegree-management
Version: 1.3.0
Summary: 
Author: Vincent Nys
Author-email: vincent.nys@ap.be
Requires-Python: >=3.10,<4.0
Classifier: Programming Language :: Python :: 3
Classifier: Programming Language :: Python :: 3.10
Requires-Dist: PyYAML (>=6.0,<7.0)
Requires-Dist: click (>=8.1.3,<9.0.0)
Requires-Dist: graphviz (>=0.20.1,<0.21.0)
Requires-Dist: networkx (>=3.0,<4.0)
Requires-Dist: pydantic (>=1.10.2,<2.0.0)
Requires-Dist: pydantic-yaml (>=0.8.1,<0.9.0)
Requires-Dist: types-PyYAML (>=6.0.12,<7.0.0)
